AUTHORS
LICENSE
MANIFEST.in
README.rst
setup.py
wasabi/__init__.py
wasabi.physics.egg-info/PKG-INFO
wasabi.physics.egg-info/SOURCES.txt
wasabi.physics.egg-info/dependency_links.txt
wasabi.physics.egg-info/namespace_packages.txt
wasabi.physics.egg-info/requires.txt
wasabi.physics.egg-info/top_level.txt
wasabi/physics/__init__.py