Metadata-Version: 1.1
Name: wasabi.physics
Version: 0.1.1
Summary: Pure python 2D physics engine
Home-page: https://bitbucket.org/lordmauve/wasabi-physics
Author: Daniel Pope
Author-email: mauve@mauveweb.co.uk
License: UNKNOWN
Platform: UNKNOWN
Classifier: Development Status :: 3 - Alpha
Classifier: License :: OSI Approved :: BSD License
Classifier: Programming Language :: Python :: 2 :: Only
Classifier: Operating System :: OS Independent
Classifier: Topic :: Software Development :: Libraries :: Python Modules
